ogc4_interface/__init__.py
ogc4_interface/_version.py
ogc4_interface/build_cache.py
ogc4_interface/cacher.py
ogc4_interface/event.py
ogc4_interface/logger.py
ogc4_interface/observing_run.py
ogc4_interface/population_mcz.py
ogc4_interface/summary.py
ogc4_interface/ogc_prior/__init__.py
ogc4_interface/ogc_prior/cosmology.py
ogc4_interface/ogc_prior/ogc_prior.py
ogc4_interface/plotting/__init__.py
ogc4_interface/plotting/cmap_generator.py
ogc4_interface/plotting/plotting.py
compas_surrogate.ogc4_interface-0.0.1.dist-info/METADATA
compas_surrogate.ogc4_interface-0.0.1.dist-info/WHEEL
compas_surrogate.ogc4_interface-0.0.1.dist-info/top_level.txt
compas_surrogate.ogc4_interface-0.0.1.dist-info/RECORD
