Metadata-Version: 2.1
Name: compas_surrogate.ogc4_interface
Version: 0.0.1
Summary: Interface to OGC-4 (https://github.com/gwastro/4-ogc)
Author-email: Avi Vajpeyi <avi.vajpeyi@gmail.com>
Project-URL: Homepage, https://github.com/COMPAS-Surrogate/ogc4_interface
Project-URL: Bug Reports, https://github.com/COMPAS-Surrogate/ogc4_interface/issues
Project-URL: Source, https://github.com/COMPAS-Surrogate/ogc4_interface/
Classifier: Development Status :: 3 - Alpha
Classifier: Intended Audience :: Science/Research
Classifier: License :: OSI Approved :: MIT License
Classifier: Operating System :: OS Independent
Classifier: Programming Language :: Python :: 3.8
Requires-Python: >=3.8
Requires-Dist: pycbc>=2.7.0
Requires-Dist: colorlog
Requires-Dist: tqdm
Requires-Dist: h5py
Requires-Dist: matplotlib
Requires-Dist: pandas
Requires-Dist: seaborn
Requires-Dist: colormath
Provides-Extra: dev
Requires-Dist: pytest>=6.0; extra == "dev"
Requires-Dist: pytest-cov>=4.1.0; extra == "dev"
Requires-Dist: coverage[toml]; extra == "dev"
Requires-Dist: pre-commit; extra == "dev"
Requires-Dist: flake8>=5.0.4; extra == "dev"
Requires-Dist: black==22.10.0; extra == "dev"
Requires-Dist: jupyter-book; extra == "dev"
Requires-Dist: pydata_sphinx_theme; extra == "dev"
